csaad_crypto2/.DS_Store
csaad_crypto2/__init__.py
csaad_crypto2/app.py
csaad_crypto2/assets/.DS_Store
csaad_crypto2/assets/.Rhistory
csaad_crypto2/assets/Bitcoin-Logo.ico
csaad_crypto2/assets/style.css
csaad_crypto2-0.1.0.dist-info/WHEEL
csaad_crypto2-0.1.0.dist-info/METADATA
csaad_crypto2-0.1.0.dist-info/RECORD
