Metadata-Version: 2.1
Name: csaad-crypto2
Version: 0.1.0
Summary: 
Author: Carlos Saad
Author-email: csaad@alumni.unav.es
Requires-Python: >=3.8,<4.0
Classifier: Programming Language :: Python :: 3
Classifier: Programming Language :: Python :: 3.10
Classifier: Programming Language :: Python :: 3.8
Classifier: Programming Language :: Python :: 3.9
Requires-Dist: dash (>=2.0.0,<3.0.0)
Requires-Dist: krakenex (>=2.1.0,<3.0.0)
Requires-Dist: pandas (>=1.3.4,<2.0.0)
Requires-Dist: plotly (>=5.4.0,<6.0.0)
Requires-Dist: pykrakenapi (>=0.2.3,<0.3.0)
